starfyre/__init__.py
starfyre/__main__.py
starfyre/cli.py
starfyre/compiler.py
starfyre/component.py
starfyre/dist_builder.py
starfyre/dom_methods.py
starfyre/exceptions.py
starfyre/file_router.py
starfyre/global_components.py
starfyre/js/__init__.py
starfyre/js/dom_helpers.py
starfyre/js/starfyre.py
starfyre/js/store.py
starfyre/parser.py
starfyre/transpiler.py
starfyre-0.21.0.dist-info/entry_points.txt
starfyre-0.21.0.dist-info/METADATA
starfyre-0.21.0.dist-info/WHEEL
starfyre-0.21.0.dist-info/RECORD
