Metadata-Version: 2.1
Name: starfyre
Version: 0.21.0
Summary: A Python Framework for writing Reactive web Front-Ends
License: BSD 2.0
Author: Sanskar Jethi
Author-email: sansyrox@gmail.com
Requires-Python: >=3.10,<4.0
Classifier: License :: Other/Proprietary License
Classifier: Programming Language :: Python :: 3
Classifier: Programming Language :: Python :: 3.10
Classifier: Programming Language :: Python :: 3.11
Classifier: Programming Language :: Python :: 3.12
Requires-Dist: click (>=8.1.3,<9.0.0)
Requires-Dist: requests (>=2.29.0,<3.0.0)
Requires-Dist: toml (>=0.10.2,<0.11.0)
